{"v":"5.5.1","fr":30,"ip":0,"op":47,"w":30,"h":89,"nm":"vertical_swipe_edu_lottie","ddd":0,"assets":[],"layers":[{"ddd":0,"ind":1,"ty":4,"nm":"Blob","sr":1,"ks":{"o":{"a":1,"k":[{"i":{"x":[0.833],"y":[0.833]},"o":{"x":[0.167],"y":[0.167]},"t":2,"s":[0]},{"i":{"x":[0.833],"y":[0.833]},"o":{"x":[0.167],"y":[0.167]},"t":5,"s":[100]},{"i":{"x":[0.833],"y":[0.833]},"o":{"x":[0.167],"y":[0.167]},"t":18,"s":[100]},{"t":24,"s":[0]}],"ix":11},"r":{"a":0,"k":0,"ix":10},"p":{"s":true,"x":{"a":0,"k":15,"ix":3},"y":{"a":1,"k":[{"i":{"x":[0.294],"y":[1]},"o":{"x":[0.519],"y":[-0.011]},"t":2,"s":[73.426]},{"t":24,"s":[15.426]}],"ix":4}},"a":{"a":0,"k":[0,0,0],"ix":1},"s":{"a":0,"k":[100,100,100],"ix":6}},"ao":0,"shapes":[{"ty":"gr","it":[{"ty":"rc","d":1,"s":{"a":1,"k":[{"i":{"x":[0.833,0.833],"y":[0.833,0.833]},"o":{"x":[0.167,0.167],"y":[0.167,0.167]},"t":2,"s":[24,24]},{"i":{"x":[0.833,0.833],"y":[0.833,0.833]},"o":{"x":[0.167,0.167],"y":[0.167,0.167]},"t":3,"s":[24,24.104]},{"i":{"x":[0.833,0.833],"y":[0.833,0.833]},"o":{"x":[0.167,0.167],"y":[0.167,0.167]},"t":4,"s":[24,24.575]},{"i":{"x":[0.833,0.833],"y":[0.833,0.833]},"o":{"x":[0.167,0.167],"y":[0.167,0.167]},"t":5,"s":[24,25.495]},{"i":{"x":[0.833,0.833],"y":[0.833,0.833]},"o":{"x":[0.167,0.167],"y":[0.167,0.167]},"t":6,"s":[24,26.731]},{"i":{"x":[0.833,0.833],"y":[0.833,0.833]},"o":{"x":[0.167,0.167],"y":[0.167,0.167]},"t":7,"s":[24,28.313]},{"i":{"x":[0.833,0.833],"y":[0.833,0.833]},"o":{"x":[0.167,0.167],"y":[0.167,0.167]},"t":8,"s":[24,30.36]},{"i":{"x":[0.833,0.833],"y":[0.833,0.833]},"o":{"x":[0.167,0.167],"y":[0.167,0.167]},"t":9,"s":[24,32.977]},{"i":{"x":[0.833,0.833],"y":[0.833,0.833]},"o":{"x":[0.167,0.167],"y":[0.167,0.167]},"t":10,"s":[24,36.078]},{"i":{"x":[0.833,0.833],"y":[0.833,0.833]},"o":{"x":[0.167,0.167],"y":[0.167,0.167]},"t":11,"s":[24,39.028]},{"i":{"x":[0.833,0.833],"y":[0.833,0.833]},"o":{"x":[0.167,0.167],"y":[0.167,0.167]},"t":12,"s":[24,40.64]},{"i":{"x":[0.833,0.833],"y":[0.833,0.833]},"o":{"x":[0.167,0.167],"y":[0.167,0.167]},"t":13,"s":[24,40.158]},{"i":{"x":[0.833,0.833],"y":[0.833,0.833]},"o":{"x":[0.167,0.167],"y":[0.167,0.167]},"t":14,"s":[24,38.049]},{"i":{"x":[0.833,0.833],"y":[0.833,0.833]},"o":{"x":[0.167,0.167],"y":[0.167,0.167]},"t":15,"s":[24,35.43]},{"i":{"x":[0.833,0.833],"y":[0.833,0.833]},"o":{"x":[0.167,0.167],"y":[0.167,0.167]},"t":16,"s":[24,33.041]},{"i":{"x":[0.833,0.833],"y":[0.833,0.833]},"o":{"x":[0.167,0.167],"y":[0.167,0.167]},"t":17,"s":[24,31.081]},{"i":{"x":[0.833,0.833],"y":[0.833,0.833]},"o":{"x":[0.167,0.167],"y":[0.167,0.167]},"t":18,"s":[24,29.514]},{"i":{"x":[0.833,0.833],"y":[0.833,0.833]},"o":{"x":[0.167,0.167],"y":[0.167,0.167]},"t":19,"s":[24,28.257]},{"i":{"x":[0.833,0.833],"y":[0.833,0.833]},"o":{"x":[0.167,0.167],"y":[0.167,0.167]},"t":20,"s":[24,27.235]},{"i":{"x":[0.833,0.833],"y":[0.833,0.833]},"o":{"x":[0.167,0.167],"y":[0.167,0.167]},"t":21,"s":[24,26.392]},{"i":{"x":[0.833,0.833],"y":[0.833,0.833]},"o":{"x":[0.167,0.167],"y":[0.167,0.167]},"t":22,"s":[24,25.685]},{"i":{"x":[0.833,0.833],"y":[0.833,0.833]},"o":{"x":[0.167,0.167],"y":[0.167,0.167]},"t":23,"s":[24,25.084]},{"i":{"x":[0.833,0.833],"y":[0.833,0.833]},"o":{"x":[0.167,0.167],"y":[0.167,0.167]},"t":24,"s":[24,24.567]},{"i":{"x":[0.833,0.833],"y":[0.833,0.833]},"o":{"x":[0.167,0.167],"y":[0.167,0.167]},"t":25,"s":[24,24.195]},{"i":{"x":[0.833,0.833],"y":[0.833,0.833]},"o":{"x":[0.167,0.167],"y":[0.167,0.167]},"t":26,"s":[24,24.021]},{"t":27,"s":[24,24]}],"ix":2,"x":"var $bm_rt;\n$bm_rt = value;"},"p":{"a":1,"k":[{"i":{"x":0.833,"y":0.833},"o":{"x":0.167,"y":0.167},"t":2,"s":[0,0],"to":[0,0.009],"ti":[0,-0.047]},{"i":{"x":0.833,"y":0.833},"o":{"x":0.167,"y":0.167},"t":3,"s":[0,0.052],"to":[0,0.047],"ti":[0,-0.093]},{"i":{"x":0.833,"y":0.833},"o":{"x":0.167,"y":0.167},"t":4,"s":[0,0.282],"to":[0,0.093],"ti":[0,-0.123]},{"i":{"x":0.833,"y":0.833},"o":{"x":0.167,"y":0.167},"t":5,"s":[0,0.608],"to":[0,0.123],"ti":[0,-0.158]},{"i":{"x":0.833,"y":0.833},"o":{"x":0.167,"y":0.167},"t":6,"s":[0,1.022],"to":[0,0.158],"ti":[0,-0.204]},{"i":{"x":0.833,"y":0.833},"o":{"x":0.167,"y":0.167},"t":7,"s":[0,1.554],"to":[0,0.204],"ti":[0,-0.262]},{"i":{"x":0.833,"y":0.833},"o":{"x":0.167,"y":0.167},"t":8,"s":[0,2.246],"to":[0,0.262],"ti":[0,-0.312]},{"i":{"x":0.833,"y":0.833},"o":{"x":0.167,"y":0.167},"t":9,"s":[0,3.124],"to":[0,0.312],"ti":[0,-0.301]},{"i":{"x":0.833,"y":0.833},"o":{"x":0.167,"y":0.167},"t":10,"s":[0,4.12],"to":[0,0.301],"ti":[0,-0.167]},{"i":{"x":0.833,"y":0.833},"o":{"x":0.167,"y":0.167},"t":11,"s":[0,4.932],"to":[0,0.167],"ti":[0,0.052]},{"i":{"x":0.833,"y":0.833},"o":{"x":0.167,"y":0.167},"t":12,"s":[0,5.119],"to":[0,-0.052],"ti":[0,0.217]},{"i":{"x":0.833,"y":0.833},"o":{"x":0.167,"y":0.167},"t":13,"s":[0,4.621],"to":[0,-0.217],"ti":[0,0.265]},{"i":{"x":0.833,"y":0.833},"o":{"x":0.167,"y":0.167},"t":14,"s":[0,3.816],"to":[0,-0.265],"ti":[0,0.239]},{"i":{"x":0.833,"y":0.833},"o":{"x":0.167,"y":0.167},"t":15,"s":[0,3.033],"to":[0,-0.239],"ti":[0,0.196]},{"i":{"x":0.833,"y":0.833},"o":{"x":0.167,"y":0.167},"t":16,"s":[0,2.38],"to":[0,-0.196],"ti":[0,0.156]},{"i":{"x":0.833,"y":0.833},"o":{"x":0.167,"y":0.167},"t":17,"s":[0,1.859],"to":[0,-0.156],"ti":[0,0.125]},{"i":{"x":0.833,"y":0.833},"o":{"x":0.167,"y":0.167},"t":18,"s":[0,1.442],"to":[0,-0.125],"ti":[0,0.102]},{"i":{"x":0.833,"y":0.833},"o":{"x":0.167,"y":0.167},"t":19,"s":[0,1.106],"to":[0,-0.102],"ti":[0,0.084]},{"i":{"x":0.833,"y":0.833},"o":{"x":0.167,"y":0.167},"t":20,"s":[0,0.831],"to":[0,-0.084],"ti":[0,0.071]},{"i":{"x":0.833,"y":0.833},"o":{"x":0.167,"y":0.167},"t":21,"s":[0,0.601],"to":[0,-0.071],"ti":[0,0.06]},{"i":{"x":0.833,"y":0.833},"o":{"x":0.167,"y":0.167},"t":22,"s":[0,0.407],"to":[0,-0.06],"ti":[0,0.052]},{"i":{"x":0.833,"y":0.833},"o":{"x":0.167,"y":0.167},"t":23,"s":[0,0.241],"to":[0,-0.052],"ti":[0,0.038]},{"i":{"x":0.833,"y":0.833},"o":{"x":0.167,"y":0.167},"t":24,"s":[0,0.097],"to":[0,-0.038],"ti":[0,0.016]},{"i":{"x":0.833,"y":0.833},"o":{"x":0.167,"y":0.167},"t":25,"s":[0,0.01],"to":[0,-0.016],"ti":[0,0.002]},{"t":26,"s":[0,0]}],"ix":3},"r":{"a":0,"k":1000,"ix":4},"nm":"Rectangle Path 1","mn":"ADBE Vector Shape - Rect","hd":false},{"ty":"st","c":{"a":0,"k":[1,1,1,1],"ix":3},"o":{"a":0,"k":100,"ix":4},"w":{"a":0,"k":2,"ix":5},"lc":1,"lj":1,"ml":4,"bm":0,"nm":"Stroke 1","mn":"ADBE Vector Graphic - Stroke","hd":false},{"ty":"fl","c":{"a":0,"k":[1,1,1,1],"ix":4},"o":{"a":0,"k":30,"ix":5},"r":1,"bm":0,"nm":"Fill 1","mn":"ADBE Vector Graphic - Fill","hd":false},{"ty":"tr","p":{"a":0,"k":[0,0],"ix":2},"a":{"a":0,"k":[0,0],"ix":1},"s":{"a":0,"k":[100,100],"ix":3},"r":{"a":1,"k":[{"i":{"x":[0.833],"y":[0.833]},"o":{"x":[0.167],"y":[0.167]},"t":2,"s":[90]},{"i":{"x":[0.833],"y":[0.833]},"o":{"x":[0.167],"y":[0.167]},"t":3,"s":[0]},{"i":{"x":[0.833],"y":[0.833]},"o":{"x":[0.167],"y":[0.167]},"t":25,"s":[0]},{"t":26,"s":[90]}],"ix":6},"o":{"a":0,"k":100,"ix":7},"sk":{"a":0,"k":0,"ix":4},"sa":{"a":0,"k":0,"ix":5},"nm":"Transform"}],"nm":"Rectangle 1","np":3,"cix":2,"bm":0,"ix":1,"mn":"ADBE Vector Group","hd":false}],"ip":0,"op":47,"st":0,"bm":0}],"markers":[]}